tspsolve/__about__.py
tspsolve/__init__.py
tspsolve/main.py
tspsolve-0.1.0.dist-info/METADATA
tspsolve-0.1.0.dist-info/RECORD
tspsolve-0.1.0.dist-info/WHEEL
tspsolve-0.1.0.dist-info/entry_points.txt
tspsolve-0.1.0.dist-info/top_level.txt
